FoamMon/FoamDataStructures.py
FoamMon/Log.py
FoamMon/__init__.py
FoamMon/cui.py
FoamMon/header.py
FoamMon/version.py
foamMon-0.2.4.data/scripts/foamMon
foamMon-0.2.4.dist-info/METADATA
foamMon-0.2.4.dist-info/RECORD
foamMon-0.2.4.dist-info/WHEEL
foamMon-0.2.4.dist-info/top_level.txt
