Metadata-Version: 2.1
Name: foamMon
Version: 0.2.4
Summary: UNKNOWN
Home-page: UNKNOWN
Author: Gregor Olenik
Author-email: go@hpsim.de
License: MIT
Platform: UNKNOWN
Requires-Dist: docopt
Requires-Dist: colorama
Requires-Dist: urwid
